cwlogcleaner/__init__.py
cwlogcleaner/cli.py
cwlogcleaner-0.1.0.dist-info/LICENSE
cwlogcleaner-0.1.0.dist-info/METADATA
cwlogcleaner-0.1.0.dist-info/WHEEL
cwlogcleaner-0.1.0.dist-info/entry_points.txt
cwlogcleaner-0.1.0.dist-info/top_level.txt
cwlogcleaner-0.1.0.dist-info/RECORD
