Metadata-Version: 2.1
Name: cwlogcleaner
Version: 0.1.0
Summary: Utility to cleanup CloudWatch logs.
Home-page: https://github.com/taimos/cwlogcleaner
Author: Thorsten Hoeger
Author-email: thorsten.hoeger@taimos.de
License: MIT
Keywords: aws,cloud,cloudwatch,logs
Platform: UNKNOWN
Classifier: Intended Audience :: Developers
Classifier: Topic :: Utilities
Classifier: License :: Public Domain
Classifier: Natural Language :: English
Classifier: Operating System :: OS Independent
Classifier: Programming Language :: Python :: 3
Classifier: Programming Language :: Python :: 3.2
Classifier: Programming Language :: Python :: 3.3
Classifier: Programming Language :: Python :: 3.4
Requires-Dist: boto3
Requires-Dist: inquirer
